Classfile /Users/liulixin/CLionProjects/jvmcpp/ch01/test/testResource/jvmgo/book/ch03/ClassFileTest0.class
  Last modified 2020-12-3; size 939 bytes
  MD5 checksum 01c4c7ae766ee2a96ec604799737ac0e
  Compiled from "ClassFileTest.java"
public class jvmgo.book.ch03.ClassFileTest
  minor version: 0
  major version: 52
  flags: ACC_PUBLIC, ACC_SUPER
Constant pool:
   #1 = Methodref          #7.#50         // java/lang/Object."<init>":()V
   #2 = Fieldref           #51.#52        // java/lang/System.out:Ljava/io/PrintStream;
   #3 = String             #53            // Hello, World!
   #4 = Methodref          #54.#55        // java/io/PrintStream.println:(Ljava/lang/String;)V
   #5 = String             #56            // 你好，世界！
   #6 = Class              #57            // jvmgo/book/ch03/ClassFileTest
   #7 = Class              #58            // java/lang/Object
   #8 = Utf8               FLAG
   #9 = Utf8               Z
  #10 = Utf8               ConstantValue
  #11 = Integer            1
  #12 = Utf8               BYTE
  #13 = Utf8               B
  #14 = Integer            123
  #15 = Utf8               X
  #16 = Utf8               C
  #17 = Integer            88
  #18 = Utf8               SHORT
  #19 = Utf8               S
  #20 = Integer            12345
  #21 = Utf8               INT
  #22 = Utf8               I
  #23 = Integer            123456789
  #24 = Utf8               LONG
  #25 = Utf8               J
  #26 = Long               12345678901l
  #28 = Utf8               PI
  #29 = Utf8               F
  #30 = Float              3.14f
  #31 = Utf8               E
  #32 = Utf8               D
  #33 = Double             2.71828d
  #35 = Utf8               <init>
  #36 = Utf8               ()V
  #37 = Utf8               Code
  #38 = Utf8               LineNumberTable
  #39 = Utf8               LocalVariableTable
  #40 = Utf8               this
  #41 = Utf8               Ljvmgo/book/ch03/ClassFileTest;
  #42 = Utf8               main
  #43 = Utf8               ([Ljava/lang/String;)V
  #44 = Utf8               args
  #45 = Utf8               [Ljava/lang/String;
  #46 = Utf8               Exceptions
  #47 = Class              #59            // java/lang/RuntimeException
  #48 = Utf8               SourceFile
  #49 = Utf8               ClassFileTest.java
  #50 = NameAndType        #35:#36        // "<init>":()V
  #51 = Class              #60            // java/lang/System
  #52 = NameAndType        #61:#62        // out:Ljava/io/PrintStream;
  #53 = Utf8               Hello, World!
  #54 = Class              #63            // java/io/PrintStream
  #55 = NameAndType        #64:#65        // println:(Ljava/lang/String;)V
  #56 = Utf8               你好，世界！
  #57 = Utf8               jvmgo/book/ch03/ClassFileTest
  #58 = Utf8               java/lang/Object
  #59 = Utf8               java/lang/RuntimeException
  #60 = Utf8               java/lang/System
  #61 = Utf8               out
  #62 = Utf8               Ljava/io/PrintStream;
  #63 = Utf8               java/io/PrintStream
  #64 = Utf8               println
  #65 = Utf8               (Ljava/lang/String;)V
{
  public static final boolean FLAG;
    descriptor: Z
    flags: ACC_PUBLIC, ACC_STATIC, ACC_FINAL
    ConstantValue: int 1

  public static final byte BYTE;
    descriptor: B
    flags: ACC_PUBLIC, ACC_STATIC, ACC_FINAL
    ConstantValue: int 123

  public static final char X;
    descriptor: C
    flags: ACC_PUBLIC, ACC_STATIC, ACC_FINAL
    ConstantValue: int 88

  public static final short SHORT;
    descriptor: S
    flags: ACC_PUBLIC, ACC_STATIC, ACC_FINAL
    ConstantValue: int 12345

  public static final int INT;
    descriptor: I
    flags: ACC_PUBLIC, ACC_STATIC, ACC_FINAL
    ConstantValue: int 123456789

  public static final long LONG;
    descriptor: J
    flags: ACC_PUBLIC, ACC_STATIC, ACC_FINAL
    ConstantValue: long 12345678901l

  public static final float PI;
    descriptor: F
    flags: ACC_PUBLIC, ACC_STATIC, ACC_FINAL
    ConstantValue: float 3.14f

  public static final double E;
    descriptor: D
    flags: ACC_PUBLIC, ACC_STATIC, ACC_FINAL
    ConstantValue: double 2.71828d

  public jvmgo.book.ch03.ClassFileTest();
    descriptor: ()V
    flags: ACC_PUBLIC
    Code:
      stack=1, locals=1, args_size=1
         0: aload_0
         1: invokespecial #1                  // Method java/lang/Object."<init>":()V
         4: return
      LineNumberTable:
        line 3: 0
      LocalVariableTable:
        Start  Length  Slot  Name   Signature
            0       5     0  this   Ljvmgo/book/ch03/ClassFileTest;

  public static void main(java.lang.String[]) throws java.lang.RuntimeException;
    descriptor: ([Ljava/lang/String;)V
    flags: ACC_PUBLIC, ACC_STATIC
    Code:
      stack=2, locals=1, args_size=1
         0: getstatic     #2                  // Field java/lang/System.out:Ljava/io/PrintStream;
         3: ldc           #3                  // String Hello, World!
         5: invokevirtual #4                  // Method java/io/PrintStream.println:(Ljava/lang/String;)V
         8: getstatic     #2                  // Field java/lang/System.out:Ljava/io/PrintStream;
        11: ldc           #5                  // String 你好，世界！
        13: invokevirtual #4                  // Method java/io/PrintStream.println:(Ljava/lang/String;)V
        16: return
      LineNumberTable:
        line 15: 0
        line 16: 8
        line 17: 16
      LocalVariableTable:
        Start  Length  Slot  Name   Signature
            0      17     0  args   [Ljava/lang/String;
    Exceptions:
      throws java.lang.RuntimeException
}
SourceFile: "ClassFileTest.java"
